bootstraprag/__init__.py
bootstraprag/cli.py
bootstraprag/templates/__init__.py
bootstraprag/templates/crewai/__init__.py
bootstraprag/templates/crewai/rag_with_crewai_and_llamaindex/.env
bootstraprag/templates/crewai/rag_with_crewai_and_llamaindex/__init__.py
bootstraprag/templates/crewai/rag_with_crewai_and_llamaindex/api_server.py
bootstraprag/templates/crewai/rag_with_crewai_and_llamaindex/client.py
bootstraprag/templates/crewai/rag_with_crewai_and_llamaindex/crew_agents.py
bootstraprag/templates/crewai/rag_with_crewai_and_llamaindex/llama_index_query_engine.py
bootstraprag/templates/crewai/rag_with_crewai_and_llamaindex/requirements.txt
bootstraprag/templates/crewai/rag_with_crewai_and_llamaindex/data/mlops.pdf
bootstraprag/templates/evaluations/__init__.py
bootstraprag/templates/evaluations/deep_evals/__init__.py
bootstraprag/templates/evaluations/deep_evals/main.py
bootstraprag/templates/evaluations/deep_evals/readme.md
bootstraprag/templates/evaluations/mlflow_evals/__init__.py
bootstraprag/templates/evaluations/mlflow_evals/basic_evaluations.py
bootstraprag/templates/evaluations/mlflow_evals/input_data.csv
bootstraprag/templates/evaluations/mlflow_evals/readme.md
bootstraprag/templates/evaluations/mlflow_evals/requirements.txt
bootstraprag/templates/evaluations/phoenix_evals/.env
bootstraprag/templates/evaluations/phoenix_evals/__init__.py
bootstraprag/templates/evaluations/phoenix_evals/basic_evaluations.py
bootstraprag/templates/evaluations/phoenix_evals/input_data.csv
bootstraprag/templates/evaluations/phoenix_evals/readme.md
bootstraprag/templates/evaluations/phoenix_evals/requirements.txt
bootstraprag/templates/evaluations/ragas_evals/.env
bootstraprag/templates/evaluations/ragas_evals/__init__.py
bootstraprag/templates/evaluations/ragas_evals/readme.md
bootstraprag/templates/evaluations/ragas_evals/requirements.txt
bootstraprag/templates/evaluations/ragas_evals/data/gold_data.json
bootstraprag/templates/evaluations/ragas_evals/data/mlops.pdf
bootstrap_rag-0.0.18.dist-info/LICENSE
bootstrap_rag-0.0.18.dist-info/METADATA
bootstrap_rag-0.0.18.dist-info/WHEEL
bootstrap_rag-0.0.18.dist-info/entry_points.txt
bootstrap_rag-0.0.18.dist-info/top_level.txt
bootstrap_rag-0.0.18.dist-info/RECORD
