Metadata-Version: 2.1
Name: bootstrap-rag
Version: 0.0.18
License-File: LICENSE
Requires-Dist: click
